{
	"info": {
		"_postman_id": "cd455a45-4f1c-4bf0-a116-8da507d24741",
		"name": "api",
		"schema": "https://schema.getpostman.com/json/collection/v2.1.0/collection.json"
	},
	"item": [
		{
			"name": "login",
			"request": {
				"method": "POST",
				"header": [],
				"body": {
					"mode": "raw",
					"raw": "{\r\n\t\"email\" : \"v123@gmail.com\",\r\n    \"password\":\"v1\"\r\n}",
					"options": {
						"raw": {
							"language": "json"
						}
					}
				},
				"url": {
					"raw": "http://localhost:8080/login",
					"protocol": "http",
					"host": [
						"localhost"
					],
					"port": "8080",
					"path": [
						"login"
					]
				}
			},
			"response": []
		},
		{
			"name": "get",
			"protocolProfileBehavior": {
				"disableBodyPruning": true
			},
			"request": {
				"auth": {
					"type": "bearer",
					"bearer": [
						{
							"key": "token",
							"value": "eyJhbGciOiJIUzI1NiIsInR5cCI6IkpXVCJ9.eyJuYW1lIjoidjEyM0BnbWFpbC5jb20iLCJ1c2VyIjp0cnVlLCJleHAiOjE2NTA3NzY3ODYsImlhdCI6MTY1MDYwMzk4NiwiaXNzIjoidmF0c2FsIn0.Sy6LC8hHR0tjYdb8K4tCCWM14fKZ51DXonfZtJozVJA",
							"type": "string"
						}
					]
				},
				"method": "GET",
				"header": [
					{
						"key": "Bearer",
						"value": "",
						"type": "default",
						"disabled": true
					}
				],
				"body": {
					"mode": "raw",
					"raw": "{\r\n\t\"email\" : \"vatsal@gmail.com\",\r\n    \"password\":\"vatsal1\"\r\n}",
					"options": {
						"raw": {
							"language": "json"
						}
					}
				},
				"url": {
					"raw": "http://localhost:8080/get",
					"protocol": "http",
					"host": [
						"localhost"
					],
					"port": "8080",
					"path": [
						"get"
					]
				}
			},
			"response": []
		},
		{
			"name": "signup",
			"request": {
				"method": "POST",
				"header": [],
				"body": {
					"mode": "raw",
					"raw": "{\r\n    \"name\" : \"vatsallll\",\r\n    \"email\" : \"v123@gmail.com\",\r\n    \"password\":\"v1\"\r\n}",
					"options": {
						"raw": {
							"language": "json"
						}
					}
				},
				"url": {
					"raw": "http://localhost:8080/signup",
					"protocol": "http",
					"host": [
						"localhost"
					],
					"port": "8080",
					"path": [
						"signup"
					]
				}
			},
			"response": []
		}
	]
}